main.py
varunsai_weather-0.1.1.dist-info/METADATA
varunsai_weather-0.1.1.dist-info/WHEEL
varunsai_weather-0.1.1.dist-info/top_level.txt
varunsai_weather-0.1.1.dist-info/RECORD
