Metadata-Version: 2.4
Name: varunsai-weather
Version: 0.1.1
Summary: My personal weather MCP server.
Requires-Python: >=3.10
Requires-Dist: httpx>=0.28.1
Requires-Dist: mcp[cli]>=1.6.0
